domain_validation/__init__.py
domain_validation/constants.py
domain_validation/creation_date.py
domain_validation/parse_date.py
domain_validation/registrar.py
domain_validation/whois.py
domain_validation/whois_client.py
domain_validation/test/__init__.py
domain_validation/test/test_whois_obj.py
domain_validation-1.6.4.dist-info/LICENSE
domain_validation-1.6.4.dist-info/METADATA
domain_validation-1.6.4.dist-info/WHEEL
domain_validation-1.6.4.dist-info/top_level.txt
domain_validation-1.6.4.dist-info/RECORD
