Metadata-Version: 2.1
Name: domain-validation
Version: 1.6.4
Summary: whois client for parsing domain creation date and registrar
Home-page: https://github.com/ElliotVilhelm/python-domain-validation
Author: Elliot Pourmand
Author-email: elliot@pourmand.com
License: UNKNOWN
Platform: UNKNOWN
Classifier: Programming Language :: Python :: 3
Classifier: License :: OSI Approved :: MIT License
Classifier: Operating System :: OS Independent
